arcade_box_api/__init__.py
arcade_box_api/tools/__init__.py
arcade_box_api/wrapper_tools/AbortUploadSession.json
arcade_box_api/wrapper_tools/CancelSignRequest.json
arcade_box_api/wrapper_tools/CheckUserInviteStatus.json
arcade_box_api/wrapper_tools/CheckZipDownloadStatus.json
arcade_box_api/wrapper_tools/DeleteAiAgent.json
arcade_box_api/wrapper_tools/DeleteArchive.json
arcade_box_api/wrapper_tools/DeleteBoxFileVersion.json
arcade_box_api/wrapper_tools/DeleteBoxHub.json
arcade_box_api/wrapper_tools/DeleteBoxHubCollaboration.json
arcade_box_api/wrapper_tools/DeleteCollaboration.json
arcade_box_api/wrapper_tools/DeleteComment.json
arcade_box_api/wrapper_tools/DeleteDevicePin.json
arcade_box_api/wrapper_tools/DeleteFileFromBox.json
arcade_box_api/wrapper_tools/DeleteFileMetadata.json
arcade_box_api/wrapper_tools/DeleteFileRequest.json
arcade_box_api/wrapper_tools/DeleteFolder.json
arcade_box_api/wrapper_tools/DeleteFolderLock.json
arcade_box_api/wrapper_tools/DeleteFolderMetadata.json
arcade_box_api/wrapper_tools/DeleteGroup.json
arcade_box_api/wrapper_tools/DeleteGroupMembership.json
arcade_box_api/wrapper_tools/DeleteLegalHoldPolicy.json
arcade_box_api/wrapper_tools/DeleteMetadataCascadePolicy.json
arcade_box_api/wrapper_tools/DeleteMetadataTemplate.json
arcade_box_api/wrapper_tools/DeleteRetentionPolicy.json
arcade_box_api/wrapper_tools/DeleteShieldBarrierSegmentRestriction.json
arcade_box_api/wrapper_tools/DeleteShieldInformationBarrierSegment.json
arcade_box_api/wrapper_tools/DeleteShieldListById.json
arcade_box_api/wrapper_tools/DeleteSlackIntegrationMapping.json
arcade_box_api/wrapper_tools/DeleteStoragePolicyAssignment.json
arcade_box_api/wrapper_tools/DeleteTaskAssignment.json
arcade_box_api/wrapper_tools/DeleteTaskFromFile.json
arcade_box_api/wrapper_tools/DeleteTeamsIntegrationMapping.json
arcade_box_api/wrapper_tools/DeleteUserAccount.json
arcade_box_api/wrapper_tools/DeleteWebLink.json
arcade_box_api/wrapper_tools/DeleteWebhook.json
arcade_box_api-1.0.0.dist-info/METADATA
arcade_box_api-1.0.0.dist-info/WHEEL
arcade_box_api-1.0.0.dist-info/licenses/LICENSE
arcade_box_api-1.0.0.dist-info/RECORD
